mdweaver/__init__.py
mdweaver/generate_pdf.py
mdweaver-0.1.0.dist-info/METADATA
mdweaver-0.1.0.dist-info/WHEEL
mdweaver-0.1.0.dist-info/entry_points.txt
mdweaver-0.1.0.dist-info/licenses/LICENSE
mdweaver-0.1.0.dist-info/RECORD
