Metadata-Version: 2.4
Name: mdweaver
Version: 0.1.0
Summary: Weave markdown files into beautifully formatted PDFs and EPUBs
Project-URL: Homepage, https://github.com/bbelderbos/mdweaver
Project-URL: Repository, https://github.com/bbelderbos/mdweaver
Author-email: Bob Belderbos <bobbelderbos@gmail.com>
License-File: LICENSE
Keywords: converter,documentation,epub,markdown,pdf
Classifier: Development Status :: 4 - Beta
Classifier: Environment :: Console
Classifier: Intended Audience :: Developers
Classifier: License :: OSI Approved :: MIT License
Classifier: Programming Language :: Python :: 3
Classifier: Programming Language :: Python :: 3.12
Classifier: Programming Language :: Python :: 3.13
Classifier: Topic :: Documentation
Classifier: Topic :: Text Processing :: Markup :: Markdown
Requires-Python: >=3.12
Requires-Dist: ebooklib>=0.20
Requires-Dist: markdown>=3.5
Requires-Dist: pygments>=2.17
Requires-Dist: weasyprint>=60.0
